<Map>
<Name>Station Config</Name>
<NumElts>1</NumElts>
<KeyValPair>
<String>
<Name>key</Name>
<Val>1</Val>
</String>
<Map>
<Name>map</Name>
<NumElts>2</NumElts>
<KeyValPair>
<I32>
<Name>Station</Name>
<Val>0</Val>
</I32>
<Cluster>
<Name>value</Name>
<NumElts>2</NumElts>
<Path>
<Name>SeqFilename</Name>
<Val>D:\用户界面\Sequence.xseq</Val>
</Path>
<I32>
<Name>NumberOfSocket</Name>
<Val>1</Val>
</I32>
</Cluster>
</KeyValPair>
<KeyValPair>
<I32>
<Name>Station</Name>
<Val>1</Val>
</I32>
<Cluster>
<Name>value</Name>
<NumElts>2</NumElts>
<Path>
<Name>SeqFilename</Name>
<Val>D:\用户界面\Sensata.xseq</Val>
</Path>
<I32>
<Name>NumberOfSocket</Name>
<Val>1</Val>
</I32>
</Cluster>
</KeyValPair>
</Map>
</KeyValPair>
</Map>

on</Name>
<Val>2</Val>
</I32>
<Cluster>
<Name>value</Name>
<NumElts>2</NumElts>
<Path>
<Name>SeqFilename</Name>
<Val>D:\用户界面\Sensata.xseq</Val>
</Path>
<I32>
<Name>NumberOfSocket</Name>
<Val>1</Val>
</I32>
</Cluster>
</KeyValPair>
</Map>
</KeyValPair>
</Map>
air>
<String>
<Name>key</Name>
<Val>B</Val>
</String>
<Map>
<Name>map</Name>
<NumElts>1</NumElts>
<KeyValPair>
<I32>
<Name>Station</Name>
<Val>0</Val>
</I32>
<Cluster>
<Name>value</Name>
<NumElts>2</NumElts>
<Path>
<Name>SeqFilename</Name>
<Val>D:\用户界面\Sensata.xseq</Val>
</Path>
<I32>
<Name>NumberOfSocket</Name>
<Val>1</Val>
</I32>
</Cluster>
</KeyValPair>
</Map>
</KeyValPair>
</Map>
e.xseq</Val>
</Path>
<I32>
<Name>NumberOfSocket</Name>
<Val>1</Val>
</I32>
</Cluster>
</KeyValPair>
</Map>
</KeyValPair>
</Map>
